tinybus-0.2.2.dist-info/METADATA
tinybus-0.2.2.dist-info/WHEEL
tinybus-0.2.2.dist-info/entry_points.txt
tinybus-0.2.2.dist-info/licenses/LICENSE
tinybus/__init__.py
tinybus/base.py
tinybus/exceptions.py
tinybus/models.py
tinybus-0.2.2.dist-info/RECORD
