Metadata-Version: 2.4
Name: tinybus
Version: 0.2.2
Summary: A modern, minimal event bus for python inspired by Eclipse Vert.x
Keywords: event bus,event driven design,asynchronous,microservices
Author-Email: =?utf-8?q?Ram=C3=B3n_Vila_Ferreres?= <ramonvilafer@proton.me>
License-Expression: MIT
Classifier: Development Status :: 5 - Production/Stable
Classifier: Framework :: AsyncIO
Classifier: Framework :: Pydantic :: 2
Classifier: Operating System :: OS Independent
Classifier: Programming Language :: Python :: 3.12
Classifier: Topic :: Software Development :: Libraries
Project-URL: Repository, https://github.com/rmonvfer/tinybus
Requires-Python: >=3.12
Requires-Dist: pydantic>=2.10.3
